gradgen/__init__.py
gradgen/cost_gradient.py
gradgen/definitions.py
gradgen/templates/c/autograd_interface.c.tmpl
gradgen/templates/c/global_header.h.tmpl
gradgen/templates/casadi-rs/Cargo.toml
gradgen/templates/casadi-rs/build.rs
gradgen/templates/casadi-rs/lib.rs
gradgen/templates/rust/Cargo.toml
gradgen/templates/rust/lib.rs
gradgen/test/__init__.py
gradgen/test/test_gradgen.py
test/__init__.py
test/test_gradgen.py
gradgen-0.1.0.dist-info/LICENSE
gradgen-0.1.0.dist-info/METADATA
gradgen-0.1.0.dist-info/WHEEL
gradgen-0.1.0.dist-info/top_level.txt
gradgen-0.1.0.dist-info/RECORD
