Metadata-Version: 2.1
Name: gradgen
Version: 0.1.0
Summary: Gradient computation with AD for optimal control
Home-page: https://github.com/alphaville/gradgen
Author: ['Jie Lin', 'Pantelis Sopasakis']
Author-email: p.sopasakis@gmail.com
License: MIT License
Keywords: optimization,nonconvex,embedded
Classifier: Development Status :: 4 - Beta
Classifier: License :: OSI Approved :: MIT License
Classifier: Programming Language :: Python
Classifier: Programming Language :: Rust
Classifier: Intended Audience :: Science/Research
Classifier: Topic :: Software Development :: Libraries
Classifier: Topic :: Scientific/Engineering
Classifier: Topic :: Scientific/Engineering :: Mathematics
Classifier: Topic :: Software Development :: Code Generators
Classifier: Topic :: Software Development :: Embedded Systems
License-File: LICENSE
Requires-Dist: jinja2
Requires-Dist: casadi
Requires-Dist: numpy
